laine-0.1.8.dist-info/licenses/LICENSE
src/__init__.py
src/__main__.py
src/cli.py
laine-0.1.8.dist-info/METADATA
laine-0.1.8.dist-info/WHEEL
laine-0.1.8.dist-info/entry_points.txt
laine-0.1.8.dist-info/top_level.txt
laine-0.1.8.dist-info/RECORD
