Metadata-Version: 2.4
Name: laine
Version: 0.1.8
Summary: A CLI tool to deobfuscate & download manga chapters from multiple official Japanese providers.
Home-page: https://github.com/syvixor/laine
Author: syvixor
License: MIT
Classifier: Programming Language :: Python :: 3
Classifier: License :: OSI Approved :: MIT License
Classifier: Operating System :: OS Independent
Classifier: Environment :: Console
Requires-Python: >=3.7
License-File: LICENSE
Requires-Dist: requests
Requires-Dist: beautifulsoup4
Requires-Dist: pillow
Requires-Dist: tqdm
Requires-Dist: lxml
Requires-Dist: questionary
Dynamic: author
Dynamic: classifier
Dynamic: description
Dynamic: description-content-type
Dynamic: home-page
Dynamic: license
Dynamic: license-file
Dynamic: requires-dist
Dynamic: requires-python
Dynamic: summary
